{"type":"excalidraw","version":2,"source":"https://libraries.excalidraw.com/libraries/mwc360/microsoft-fabric-architecture-icons.excalidrawlib","elements":[{"type":"text","version":1496,"versionNonce":58817287,"isDeleted":false,"id":"Q0CFxOkqevWQv5muy6Biy","fillStyle":"solid","strokeWidth":1,"strokeStyle":"solid","roughness":1,"opacity":100,"angle":0,"x":0.0,"y":82.1914245327423,"strokeColor":"#1e1e1e","backgroundColor":"#1595d5","width":105.90394592285156,"height":40,"seed":532828959,"groupIds":["ikHnP6RoTP7kthQbAMwU3","MXBtMhOkfJVD7ks2PBD1J","mP_g9tA0uf_Mg4mZw-nrY","WBmIX842FSc4Luc_7mrpq","zbYf5atP283oN8hkwIjcj","SwnxTvSTa1DAbu5zLg2Cd"],"frameId":null,"roundness":null,"boundElements":[],"updated":1747092464194,"link":null,"locked":false,"fontSize":16,"fontFamily":1,"text":"Bronze Delta\nTable","textAlign":"center","verticalAlign":"top","containerId":null,"originalText":"Bronze Delta\nTable","lineHeight":1.25,"baseline":34,"index":"b6z","autoResize":true},{"type":"rectangle","version":1638,"versionNonce":2009760295,"isDeleted":false,"id":"YdvHFapWSEqK38L0Jlp_c","fillStyle":"solid","strokeWidth":2,"strokeStyle":"solid","roughness":1,"opacity":100,"angle":0,"x":18.57102900806194,"y":9.30684347646752,"strokeColor":"#1e1e1e","backgroundColor":"#f1f1f1","width":62.36489919840756,"height":62.536197710052434,"seed":1425335903,"groupIds":["mfksk8xO4GDJ8PbrlhbH5","xI3LmAeycvtZ504y5RAIU","DsaDps7Y-2DEXjiDLBFYn","SwnxTvSTa1DAbu5zLg2Cd"],"frameId":null,"roundness":{"type":3},"boundElements":[],"updated":1747092464194,"link":null,"locked":false,"index":"b70"},{"type":"line","version":1594,"versionNonce":128296263,"isDeleted":false,"id":"XmrPfrAXsVX259j2pN6SL","fillStyle":"solid","strokeWidth":1,"strokeStyle":"solid","roughness":1,"opacity":100,"angle":0,"x":18.86691153336733,"y":29.498544990944765,"strokeColor":"#1e1e1e","backgroundColor":"#f1f1f1","width":62.07422907757233,"height":0,"seed":2070332031,"groupIds":["mfksk8xO4GDJ8PbrlhbH5","xI3LmAeycvtZ504y5RAIU","DsaDps7Y-2DEXjiDLBFYn","SwnxTvSTa1DAbu5zLg2Cd"],"frameId":null,"roundness":null,"boundElements":[],"updated":1747092464194,"link":null,"locked":false,"startBinding":null,"endBinding":null,"lastCommittedPoint":null,"startArrowhead":null,"endArrowhead":null,"points":[[0,0],[62.07422907757233,0]],"index":"b71"},{"type":"line","version":1540,"versionNonce":846160999,"isDeleted":false,"id":"uB4YYbYFFcDMHVIWmq3AJ","fillStyle":"solid","strokeWidth":1,"strokeStyle":"solid","roughness":1,"opacity":100,"angle":0,"x":38.74207507742631,"y":9.611046280630262,"strokeColor":"#1e1e1e","backgroundColor":"#f1f1f1","width":0,"height":62.30299065321654,"seed":193469087,"groupIds":["mfksk8xO4GDJ8PbrlhbH5","xI3LmAeycvtZ504y5RAIU","DsaDps7Y-2DEXjiDLBFYn","SwnxTvSTa1DAbu5zLg2Cd"],"frameId":null,"roundness":null,"boundElements":[],"updated":1747092464194,"link":null,"locked":false,"startBinding":null,"endBinding":null,"lastCommittedPoint":null,"startArrowhead":null,"endArrowhead":null,"points":[[0,0],[0,62.30299065321654]],"index":"b72"},{"type":"line","version":1659,"versionNonce":1475624839,"isDeleted":false,"id":"fYm6HUqk_-OQ6h5Xoi-I0","fillStyle":"solid","strokeWidth":1,"strokeStyle":"solid","roughness":1,"opacity":100,"angle":0,"x":61.47207670822581,"y":9.976185210292215,"strokeColor":"#1e1e1e","backgroundColor":"#f1f1f1","width":0,"height":61.836031311667504,"seed":436825791,"groupIds":["mfksk8xO4GDJ8PbrlhbH5","xI3LmAeycvtZ504y5RAIU","DsaDps7Y-2DEXjiDLBFYn","SwnxTvSTa1DAbu5zLg2Cd"],"frameId":null,"roundness":null,"boundElements":[],"updated":1747092464194,"link":null,"locked":false,"startBinding":null,"endBinding":null,"lastCommittedPoint":null,"startArrowhead":null,"endArrowhead":null,"points":[[0,0],[0,61.836031311667504]],"index":"b73"},{"type":"line","version":1610,"versionNonce":712029863,"isDeleted":false,"id":"GgrAi2wIYVeowQSvV3uTp","fillStyle":"solid","strokeWidth":1,"strokeStyle":"solid","roughness":1,"opacity":100,"angle":0,"x":18.67649978773079,"y":50.88287592223719,"strokeColor":"#1e1e1e","backgroundColor":"#f1f1f1","width":62.07422907757233,"height":0,"seed":1368080095,"groupIds":["mfksk8xO4GDJ8PbrlhbH5","xI3LmAeycvtZ504y5RAIU","DsaDps7Y-2DEXjiDLBFYn","SwnxTvSTa1DAbu5zLg2Cd"],"frameId":null,"roundness":null,"boundElements":[],"updated":1747092464194,"link":null,"locked":false,"startBinding":null,"endBinding":null,"lastCommittedPoint":null,"startArrowhead":null,"endArrowhead":null,"points":[[0,0],[62.07422907757233,0]],"index":"b74"},{"type":"line","version":3987,"versionNonce":1620134343,"isDeleted":false,"id":"-_sFJi9CA3Hh_R1xxeSQG","fillStyle":"solid","strokeWidth":1,"strokeStyle":"solid","roughness":1,"opacity":100,"angle":0,"x":68.10253165840459,"y":34.00127372609791,"strokeColor":"#000000","backgroundColor":"#00add7","width":48.31136822171123,"height":47.07141590121103,"seed":882772735,"groupIds":["xI3LmAeycvtZ504y5RAIU","DsaDps7Y-2DEXjiDLBFYn","SwnxTvSTa1DAbu5zLg2Cd"],"frameId":null,"roundness":null,"boundElements":[],"updated":1747092464194,"link":null,"locked":false,"startBinding":null,"endBinding":null,"lastCommittedPoint":null,"startArrowhead":null,"endArrowhead":null,"points":[[0,0],[-0.24206210639618844,-0.30962157611717084],[-0.5889278204739552,-0.5954918964681293],[-1.0166608468639724,-0.7333142592248739],[-1.509690841362308,-0.6036839743900665],[-1.984909272448689,-0.3259174485443922],[-2.8886078029944544,1.2710780493231173],[-20.889659960688274,32.34131663982792],[-20.985974129713203,32.694039890797185],[-20.82473849062865,32.996903759366965],[-20.436862836900996,33.2247766950107],[-19.948298644824032,33.22635925120563],[-17.156675432261185,32.21019921592013],[-14.4624344247877,31.456274028450252],[-10.469764016122195,30.833466264888173],[-7.38599418829112,30.833466264888173],[-5.113742736205053,31.030142400749867],[-3.1985593694467913,31.489053384427194],[-0.7964649772415299,32.24297857189707],[1.0537969194571186,33.029683115343914],[1.4765406148911295,32.924214067001444],[1.5731686799339393,32.53799277568964],[0.4695036889207167,31.194039180634636],[-1.1535330625693327,30.04676172144134],[-3.2310201044766127,28.76836683834024],[-5.56819302662226,27.621089379146937],[-7.38599418829112,26.932722903630967],[-9.10641314487054,26.572149987884494],[-9.00903093978113,25.654328020529864],[-1.6079833529865628,12.903158545495808],[-0.9912293874203412,12.608144341703243],[-0.27709321676471066,13.230952105265315],[13.973169461317855,37.7499103760249],[14.038090931377473,38.47105620751783],[13.35641549575164,39.0938639710799],[11.506153599052999,39.61833366671111],[9.52604876223515,39.68389237866502],[6.961650694880866,39.71667173464198],[4.364791892496791,38.897187835218205],[2.3522263206491574,38.044924579817454],[0.5668858940100916,37.192661324416726],[-2.516883933820982,35.65203159350002],[-5.113742736205053,34.70143027016843],[-7.38599418829112,34.176960574537205],[-10.177617400854006,33.914725726721585],[-13.261387228685075,34.275298642468066],[-15.403795740651914,34.734209626145386],[-17.805890132857172,35.81592837338478],[-19.591230559496243,36.93042647660112],[-21.473953191224677,38.43827685154088],[-23.291754352893538,40.27392078625016],[-24.525262284025953,42.011226653028565],[-25.541339567317326,43.480923144975606],[-25.28198215216468,43.71605493245411],[-22.64253965229751,42.43735828072893],[-20.27290599512205,41.388418889466486],[-17.578664987648594,40.66727305797355],[-15.89070676609894,40.3067001422271],[-12.936779878387064,39.84778915854978],[-10.729449896360581,39.71667173464198],[-8.16505182900634,39.94612722648065],[-5.6980359667414575,40.732831769927465],[-3.1011771643573836,41.88010922912078],[-0.3095539517945305,43.28962153612968],[2.0276189703511496,44.469678351299926],[5.565839088599426,45.780852590377975],[8.617148181400715,46.33810164198616],[11.473692864023203,46.33810164198616],[14.622384161913876,45.813631946354924],[17.83599692986415,44.666354487161634],[19.49149441638401,43.84687058773785],[21.861128073559456,42.07678536498247],[22.607724979244885,40.896728549812224],[22.7700286543939,39.782230446595875],[22.510342774155482,38.73329105533344],[21.601442193321073,37.25822003637062],[0,0]],"index":"b75"},{"type":"ellipse","version":1560,"versionNonce":661813479,"isDeleted":false,"id":"56GHuRPg6AgiBLGDFZ9tv","fillStyle":"solid","strokeWidth":2,"strokeStyle":"solid","roughness":1,"opacity":100,"angle":0,"x":9.890002723789166,"y":0.0,"strokeColor":"#1e1e1e","backgroundColor":"#e8590c","width":24.69135802469134,"height":24.69135802469134,"seed":879716095,"groupIds":["EFgi0xKSosvBC0g-rHBIL","DsaDps7Y-2DEXjiDLBFYn","SwnxTvSTa1DAbu5zLg2Cd"],"frameId":null,"roundness":{"type":2},"boundElements":[],"updated":1747092464194,"link":null,"locked":false,"index":"b76"}],"appState":{"gridSize":null,"viewBackgroundColor":"transparent"},"files":{}}