{"type":"excalidraw","version":2,"source":"https://libraries.excalidraw.com/libraries/mwc360/microsoft-fabric-architecture-icons.excalidrawlib","elements":[{"type":"line","version":2211,"versionNonce":280155943,"isDeleted":false,"id":"Vq8vQxVgA4bwVyFw0ogfQ","fillStyle":"solid","strokeWidth":1,"strokeStyle":"solid","roughness":1,"opacity":100,"angle":0,"x":29.89852352712387,"y":0.0,"strokeColor":"#1e1e1e","backgroundColor":"#4cd9fb","width":45.607692251423074,"height":54.35797110504768,"seed":1382805791,"groupIds":["UU8d8WePxvX2DR422wt00","ZExOs_WJpf3BsjhAzk_4y","oB9SpLJi0vul6XzZsYKUw"],"frameId":null,"roundness":null,"boundElements":[],"updated":1747091766976,"link":null,"locked":false,"startBinding":null,"endBinding":null,"lastCommittedPoint":null,"startArrowhead":null,"endArrowhead":null,"points":[[0,0],[-18.15450148806282,18.682255253845867],[-18.260054173887863,42.43088481381947],[-7.388456087541476,54.35797110504768],[-9.077250744031403,43.90857409865932],[-4.433077517861707,34.514674960494936],[0.4222107433001285,27.7595059978773],[12.771498114486354,17.9434057797549],[20.68770796781092,10.766045400521353],[27.347638077535212,0.19046804244452287],[0,0]],"index":"b6M"},{"type":"line","version":2183,"versionNonce":1790663239,"isDeleted":false,"id":"BYWDuGpby0ILWXt1gig91","fillStyle":"solid","strokeWidth":1,"strokeStyle":"solid","roughness":1,"opacity":100,"angle":0,"x":34.753811788285475,"y":24.698574742372784,"strokeColor":"#1e1e1e","backgroundColor":"#059ae7","width":47.708364491597195,"height":35.67571585120177,"seed":858682687,"groupIds":["UU8d8WePxvX2DR422wt00","ZExOs_WJpf3BsjhAzk_4y","oB9SpLJi0vul6XzZsYKUw"],"frameId":null,"roundness":null,"boundElements":[],"updated":1747091766976,"link":null,"locked":false,"startBinding":null,"endBinding":null,"lastCommittedPoint":null,"startArrowhead":null,"endArrowhead":null,"points":[[0,0],[8.12729589829038,12.032638977053242],[21.532090801042706,20.26549722451074],[31.348191019165117,20.054401516202805],[34.19802656636194,18.998903647978846],[17.415661677313928,35.14797174876085],[-7.388475414225696,35.67571585120177],[-12.109942203719417,29.740038408842803],[-13.510337925235254,18.893350962153804],[-6.649616276792585,5.699671094393639],[0,0]],"index":"b6N"},{"type":"line","version":2058,"versionNonce":1929804135,"isDeleted":false,"id":"1KL-hixXyxYNyWo3wX0LV","fillStyle":"solid","strokeWidth":1,"strokeStyle":"solid","roughness":1,"opacity":100,"angle":0,"x":44.675455028891065,"y":37.78671158764985,"strokeColor":"#1e1e1e","backgroundColor":"#096cb0","width":27.759515661219375,"height":28.079602104580644,"seed":1028355423,"groupIds":["UU8d8WePxvX2DR422wt00","ZExOs_WJpf3BsjhAzk_4y","oB9SpLJi0vul6XzZsYKUw"],"frameId":null,"roundness":null,"boundElements":[],"updated":1747091766976,"link":null,"locked":false,"startBinding":null,"endBinding":null,"lastCommittedPoint":null,"startArrowhead":null,"endArrowhead":null,"points":[[0,0],[10.343853983905435,-7.282913065058552],[20.582145618643754,-17.837862757271964],[23.74862955997354,-20.793250990293807],[26.492922084687446,-18.89336062549592],[27.759515661219375,-14.143634713501227],[27.4428672670864,1.3721365990148287],[24.450178272220658,5.743847639940948],[11.845082485087099,7.286351114286837],[0,0]],"index":"b6O"},{"type":"rectangle","version":2582,"versionNonce":2128655495,"isDeleted":false,"id":"nlqZHvdYTuNJ4iq6EhT32","fillStyle":"solid","strokeWidth":1,"strokeStyle":"dashed","roughness":1,"opacity":100,"angle":0,"x":11.04676401261986,"y":0.41294394317583283,"strokeColor":"transparent","backgroundColor":"transparent","width":60.75037240124135,"height":59.54090868322488,"seed":1477669247,"groupIds":["04zsX-Jevp0J216ATqlMD","hR2kgNZeSFEKm638Farpq","dx_K9Gh7mWchFJK6L_-X9","DUgtXEWZMEQ_6yHpJa7mu","tpv3XxyfeNxEQdlMcAGL-","yu4-tEm6YZQhhR75uHaV8","hLiDgUmEqGXehGQtG58G0","em0xCIuWngceZYY6k8gBp","ZExOs_WJpf3BsjhAzk_4y","oB9SpLJi0vul6XzZsYKUw"],"frameId":null,"roundness":null,"boundElements":[],"updated":1747091766976,"link":null,"locked":false,"index":"b6P"},{"type":"text","version":656,"versionNonce":101092263,"isDeleted":false,"id":"GCIWM_rirlQtvHw9P5s0q","fillStyle":"solid","strokeWidth":1,"strokeStyle":"solid","roughness":1,"opacity":100,"angle":0,"x":0.0,"y":65.6692021577087,"strokeColor":"#1e1e1e","backgroundColor":"#1595d5","width":80.62396240234375,"height":40,"seed":2117446367,"groupIds":["RditCsCr6wrBNj6aZLZ16","oB9SpLJi0vul6XzZsYKUw"],"frameId":null,"roundness":null,"boundElements":[],"updated":1747091766976,"link":null,"locked":false,"fontSize":16,"fontFamily":1,"text":"Data\nEngineering","textAlign":"center","verticalAlign":"top","containerId":null,"originalText":"Data\nEngineering","lineHeight":1.25,"baseline":34,"index":"b6Q","autoResize":true}],"appState":{"gridSize":null,"viewBackgroundColor":"transparent"},"files":{}}