{"type":"excalidraw","version":2,"source":"https://libraries.excalidraw.com/libraries/mwc360/microsoft-fabric-architecture-icons.excalidrawlib","elements":[{"type":"rectangle","version":2182,"versionNonce":1117566377,"isDeleted":false,"id":"-704bNrtTU4ZN5aRB8_Xt","fillStyle":"solid","strokeWidth":2,"strokeStyle":"solid","roughness":1,"opacity":100,"angle":0,"x":34.83680811817658,"y":5.880202836976025,"strokeColor":"#1e1e1e","backgroundColor":"#f1f1f1","width":44.960411610322105,"height":61.11543941798723,"seed":1438934879,"groupIds":["_ZKHrnq8SaBV-vQfA_j7Z","n6nua1QHMUansyqTX9vTK","Uujvhioy5qAiPtVe86JXr","TLnTQElOxL7JEzcPaH3vc","Wb1bJJT_48tzTdrYzMWHi","_ITp0DRQco7Ibg3XveuXS"],"frameId":null,"roundness":{"type":3},"boundElements":[],"updated":1747091803438,"link":null,"locked":false,"index":"b1Z"},{"type":"rectangle","version":2101,"versionNonce":1185552521,"isDeleted":false,"id":"MB3_ALGyzIKl4LhG3cobB","fillStyle":"solid","strokeWidth":2,"strokeStyle":"solid","roughness":1,"opacity":100,"angle":0,"x":28.294667514119737,"y":0.0,"strokeColor":"#1e1e1e","backgroundColor":"#f1f1f1","width":44.960411610322105,"height":61.11543941798723,"seed":413016959,"groupIds":["ESC8L3veJ487BQzmNMSng","GUUIEvfwZHnK9ifjM-Njq","3_vR-EXCqDWkwQZ1Ms5X-","TLnTQElOxL7JEzcPaH3vc","Wb1bJJT_48tzTdrYzMWHi","_ITp0DRQco7Ibg3XveuXS"],"frameId":null,"roundness":{"type":3},"boundElements":[],"updated":1747091803438,"link":null,"locked":false,"index":"b1a"},{"type":"line","version":2261,"versionNonce":1825054569,"isDeleted":false,"id":"nTNIQP2znFnn8rgTgIBSo","fillStyle":"solid","strokeWidth":1,"strokeStyle":"solid","roughness":1,"opacity":100,"angle":0,"x":82.61573955356653,"y":54.34826118935513,"strokeColor":"#1e1e1e","backgroundColor":"#45913e","width":15.325866986049734,"height":14.797388814116932,"seed":757816223,"groupIds":["u74qw516HASUt3sp8q0x1","Wb1bJJT_48tzTdrYzMWHi","_ITp0DRQco7Ibg3XveuXS"],"frameId":null,"roundness":null,"boundElements":[],"updated":1747091803438,"link":null,"locked":false,"startBinding":null,"endBinding":null,"lastCommittedPoint":null,"startArrowhead":null,"endArrowhead":null,"points":[[0,0],[0,14.797388814116932],[-15.325866986049734,0.2113912687730677],[0,0]],"index":"b1b"},{"type":"line","version":2333,"versionNonce":1933724233,"isDeleted":false,"id":"MvSYppcAXwqKbnKGwTMM4","fillStyle":"solid","strokeWidth":1,"strokeStyle":"solid","roughness":1,"opacity":100,"angle":0,"x":66.98045648524385,"y":65.52731992549985,"strokeColor":"#1e1e1e","backgroundColor":"#45913e","width":5.4546253704432885,"height":5.755205126467269,"seed":127700927,"groupIds":["u74qw516HASUt3sp8q0x1","Wb1bJJT_48tzTdrYzMWHi","_ITp0DRQco7Ibg3XveuXS"],"frameId":null,"roundness":null,"boundElements":[],"updated":1747091803438,"link":null,"locked":false,"startBinding":null,"endBinding":null,"lastCommittedPoint":null,"startArrowhead":null,"endArrowhead":null,"points":[[0,0],[4.429597740765803,-4.714907419426982],[3.277127700073445,-5.755205126467269],[-1.0250276296774858,-0.929809303945348],[0,0]],"index":"b1c"},{"type":"line","version":2362,"versionNonce":1123293481,"isDeleted":false,"id":"zkq20s1e-6aG-MsLrAeUv","fillStyle":"solid","strokeWidth":1,"strokeStyle":"solid","roughness":1,"opacity":100,"angle":0,"x":72.18724568504695,"y":70.5962800802609,"strokeColor":"#1e1e1e","backgroundColor":"#45913e","width":5.293505539776492,"height":5.755205126467269,"seed":1108492255,"groupIds":["u74qw516HASUt3sp8q0x1","Wb1bJJT_48tzTdrYzMWHi","_ITp0DRQco7Ibg3XveuXS"],"frameId":null,"roundness":null,"boundElements":[],"updated":1747091803438,"link":null,"locked":false,"startBinding":null,"endBinding":null,"lastCommittedPoint":null,"startArrowhead":null,"endArrowhead":null,"points":[[0,0],[4.429597740765804,-4.714907419426982],[3.277127700073445,-5.755205126467269],[-0.8639077990106877,-1.2520489652788778],[0,0]],"index":"b1d"},{"type":"line","version":2707,"versionNonce":491326473,"isDeleted":false,"id":"xf04Brx8hT5e5AMZyURhM","fillStyle":"solid","strokeWidth":1,"strokeStyle":"solid","roughness":1,"opacity":100,"angle":0,"x":67.33715443535812,"y":70.05641884117159,"strokeColor":"#1e1e1e","backgroundColor":"#45913e","width":8.005990611583686,"height":7.744509159146251,"seed":1587342335,"groupIds":["u74qw516HASUt3sp8q0x1","Wb1bJJT_48tzTdrYzMWHi","_ITp0DRQco7Ibg3XveuXS"],"frameId":null,"roundness":null,"boundElements":[],"updated":1747091803438,"link":null,"locked":false,"startBinding":null,"endBinding":null,"lastCommittedPoint":null,"startArrowhead":null,"endArrowhead":null,"points":[[0,0],[6.837092391191275,-6.704211452105964],[5.684622350498919,-7.744509159146251],[-1.1688982203924105,-0.70200527115964],[0,0]],"index":"b1e"},{"type":"text","version":664,"versionNonce":171746025,"isDeleted":false,"id":"Tc1_HeLpR88cKNtd81_T-","fillStyle":"solid","strokeWidth":1,"strokeStyle":"solid","roughness":1,"opacity":100,"angle":0,"x":0.0,"y":72.01457775621344,"strokeColor":"#1e1e1e","backgroundColor":"#1595d5","width":109.69596862792969,"height":20,"seed":111878961,"groupIds":["bchVnLSjMvqadC1jEoC8p","XCzCQmgUirKIP4f4oPuJI","_ITp0DRQco7Ibg3XveuXS"],"frameId":null,"roundness":null,"boundElements":[],"updated":1747091803438,"link":null,"locked":false,"fontSize":16,"fontFamily":1,"text":"KQL QuerySet","textAlign":"center","verticalAlign":"top","containerId":null,"originalText":"KQL QuerySet","lineHeight":1.25,"baseline":14,"index":"b1f","autoResize":true}],"appState":{"gridSize":null,"viewBackgroundColor":"transparent"},"files":{}}