{"type":"excalidraw","version":2,"source":"https://libraries.excalidraw.com/libraries/mwc360/microsoft-fabric-architecture-icons.excalidrawlib","elements":[{"id":"ZAqF5izBeBF0IEBQvH5cH","type":"line","x":62.477913532510684,"y":5.360429983215909,"width":6.059199878830922,"height":15.92703968149848,"angle":0,"strokeColor":"#000000","backgroundColor":"#ffca00","fillStyle":"solid","strokeWidth":1,"strokeStyle":"solid","roughness":1,"opacity":100,"groupIds":["pXwQsk9cJkaMNmeBLRnvQ","eY5BbVWEqsCv6tbtkN19O"],"frameId":null,"index":"bHz","roundness":null,"seed":784268615,"version":609,"versionNonce":289226663,"isDeleted":false,"boundElements":[],"updated":1747092006709,"link":null,"locked":false,"points":[[0,0],[6.001493213318286,0],[6.001493213318286,15.92703968149848],[-0.05770666551263635,15.92703968149848],[0,0]],"lastCommittedPoint":null,"startBinding":null,"endBinding":null,"startArrowhead":null,"endArrowhead":null},{"id":"mJ-drUY5H5QIXWCwDA9s2","type":"line","x":62.43792912065783,"y":28.997020858360884,"width":6.053461894808148,"height":25.102238214371045,"angle":0,"strokeColor":"#000000","backgroundColor":"#ffca00","fillStyle":"solid","strokeWidth":1,"strokeStyle":"solid","roughness":1,"opacity":100,"groupIds":["pXwQsk9cJkaMNmeBLRnvQ","eY5BbVWEqsCv6tbtkN19O"],"frameId":null,"index":"bI0","roundness":null,"seed":1553841255,"version":692,"versionNonce":786739911,"isDeleted":false,"boundElements":[],"updated":1747092006709,"link":null,"locked":false,"points":[[0,0],[5.9958098767623955,0],[5.9958098767623955,25.102238214371045],[-0.057652018045752824,25.102238214371045],[0,0]],"lastCommittedPoint":null,"startBinding":null,"endBinding":null,"startArrowhead":null,"endArrowhead":null},{"id":"HPkElcA79sqeoFdhvW4aK","type":"line","x":4.23289608352934,"y":16.68979948721426,"width":6.053141863969503,"height":24.938971796249316,"angle":0,"strokeColor":"#000000","backgroundColor":"#3b3b3b","fillStyle":"solid","strokeWidth":1,"strokeStyle":"solid","roughness":1,"opacity":100,"groupIds":["pXwQsk9cJkaMNmeBLRnvQ","eY5BbVWEqsCv6tbtkN19O"],"frameId":null,"index":"bI1","roundness":null,"seed":1519884167,"version":772,"versionNonce":158384615,"isDeleted":false,"boundElements":[],"updated":1747092006709,"link":null,"locked":false,"points":[[0,0],[5.9954928938364995,0],[5.9954928938364995,24.938971796249316],[-0.05764897013300383,24.938971796249316],[0,0]],"lastCommittedPoint":null,"startBinding":null,"endBinding":null,"startArrowhead":null,"endArrowhead":null},{"id":"5Sz6TL_Nw_NigB98KCyv8","type":"rectangle","x":10.099386464472445,"y":0.0,"width":52.05982422592699,"height":58.17651375638843,"angle":0,"strokeColor":"#000000","backgroundColor":"#6fb143","fillStyle":"solid","strokeWidth":1,"strokeStyle":"solid","roughness":1,"opacity":100,"groupIds":["pXwQsk9cJkaMNmeBLRnvQ","eY5BbVWEqsCv6tbtkN19O"],"frameId":null,"index":"bI2","roundness":null,"seed":787025575,"version":544,"versionNonce":1374547207,"isDeleted":false,"boundElements":[],"updated":1747092006709,"link":null,"locked":false},{"id":"oZd51WbmIDcgvbaLGS5R4","type":"line","x":32.04835817690764,"y":36.268365793752764,"width":4.042887366670434,"height":18.47181296840838,"angle":0,"strokeColor":"#000000","backgroundColor":"#365615","fillStyle":"solid","strokeWidth":1,"strokeStyle":"solid","roughness":1,"opacity":100,"groupIds":["pXwQsk9cJkaMNmeBLRnvQ","eY5BbVWEqsCv6tbtkN19O"],"frameId":null,"index":"bI3","roundness":null,"seed":1681826247,"version":651,"versionNonce":1675146279,"isDeleted":false,"boundElements":[],"updated":1747092006709,"link":null,"locked":false,"points":[[0,0],[3.9034774574749775,0],[3.9034774574749775,18.47181296840838],[-0.13940990919545668,18.47181296840838],[0,0]],"lastCommittedPoint":null,"startBinding":null,"endBinding":null,"startArrowhead":null,"endArrowhead":null},{"id":"trmyQtLCoMrcvNr0LVIHW","type":"ellipse","x":28.789890350691167,"y":21.147911842906524,"width":8.01606977874314,"height":8.36459455173209,"angle":0,"strokeColor":"#000000","backgroundColor":"#ffffff","fillStyle":"solid","strokeWidth":1,"strokeStyle":"solid","roughness":1,"opacity":100,"groupIds":["pXwQsk9cJkaMNmeBLRnvQ","eY5BbVWEqsCv6tbtkN19O"],"frameId":null,"index":"bI4","roundness":null,"seed":2075447527,"version":500,"versionNonce":1998427975,"isDeleted":false,"boundElements":[],"updated":1747092006709,"link":null,"locked":true},{"id":"H5u-XQK30Ph7ISTxl6bqz","type":"line","x":29.138415123679806,"y":7.137215968755299,"width":10.87397291725178,"height":40.21975880291177,"angle":0,"strokeColor":"#b4ec36","backgroundColor":"#b4ec36","fillStyle":"solid","strokeWidth":2,"strokeStyle":"solid","roughness":1,"opacity":100,"groupIds":["pXwQsk9cJkaMNmeBLRnvQ","eY5BbVWEqsCv6tbtkN19O"],"frameId":null,"index":"bI5","roundness":null,"seed":517479431,"version":614,"versionNonce":303634023,"isDeleted":false,"boundElements":[],"updated":1747092006709,"link":null,"locked":false,"points":[[0,0],[-10.87397291725178,0],[-10.87397291725178,40.21975880291177],[-4.879346821843721,40.21975880291177]],"lastCommittedPoint":null,"startBinding":null,"endBinding":null,"startArrowhead":null,"endArrowhead":null},{"id":"udaJqygOPBWx5DleV1kkX","type":"line","x":28.999005214484896,"y":10.970988471632609,"width":6.970495459776667,"height":32.273393978766286,"angle":0,"strokeColor":"#b4ec36","backgroundColor":"#b4ec36","fillStyle":"solid","strokeWidth":2,"strokeStyle":"solid","roughness":1,"opacity":100,"groupIds":["pXwQsk9cJkaMNmeBLRnvQ","eY5BbVWEqsCv6tbtkN19O"],"frameId":null,"index":"bI6","roundness":null,"seed":296026919,"version":652,"versionNonce":999797127,"isDeleted":false,"boundElements":[],"updated":1747092006709,"link":null,"locked":false,"points":[[0,0],[-6.970495459776667,0],[-6.970495459776667,32.273393978766286],[-4.321707185061484,32.273393978766286]],"lastCommittedPoint":null,"startBinding":null,"endBinding":null,"startArrowhead":null,"endArrowhead":null},{"id":"bFC_37OVGPk0vEENQmZn5","type":"line","x":45.8676042271436,"y":14.804760974509918,"width":6.761380595983483,"height":28.927556158073447,"angle":0,"strokeColor":"#b4ec36","backgroundColor":"#b4ec36","fillStyle":"solid","strokeWidth":2,"strokeStyle":"solid","roughness":1,"opacity":100,"groupIds":["pXwQsk9cJkaMNmeBLRnvQ","eY5BbVWEqsCv6tbtkN19O"],"frameId":null,"index":"bI7","roundness":null,"seed":1686636103,"version":609,"versionNonce":1825958055,"isDeleted":false,"boundElements":[],"updated":1747092006709,"link":null,"locked":false,"points":[[0,0],[0,9.82839859828517],[-4.461117094257078,9.82839859828517],[-4.461117094257078,28.927556158073447],[2.3002635017264046,28.927556158073447]],"lastCommittedPoint":null,"startBinding":null,"endBinding":null,"startArrowhead":null,"endArrowhead":null},{"id":"_ltM7pHxA6KNYobhl40Ul","type":"line","x":28.999005214484896,"y":3.024623647487033,"width":23.281454835654408,"height":11.919547236218254,"angle":0,"strokeColor":"#000000","backgroundColor":"#365615","fillStyle":"solid","strokeWidth":1,"strokeStyle":"solid","roughness":1,"opacity":100,"groupIds":["pXwQsk9cJkaMNmeBLRnvQ","eY5BbVWEqsCv6tbtkN19O"],"frameId":null,"index":"bI8","roundness":null,"seed":1717413223,"version":593,"versionNonce":1132477383,"isDeleted":false,"boundElements":[],"updated":1747092006709,"link":null,"locked":false,"points":[[0,0],[0,11.849842281620491],[23.281454835654408,11.849842281620491],[23.281454835654408,-0.06970495459776256],[0,0]],"lastCommittedPoint":null,"startBinding":null,"endBinding":null,"startArrowhead":null,"endArrowhead":null},{"id":"UfJg0f16MJg0pQRsNVyZY","type":"line","x":24.607593074824763,"y":36.27388699062203,"width":4.042887366670434,"height":18.47181296840838,"angle":0,"strokeColor":"#000000","backgroundColor":"#365615","fillStyle":"solid","strokeWidth":1,"strokeStyle":"solid","roughness":1,"opacity":100,"groupIds":["pXwQsk9cJkaMNmeBLRnvQ","eY5BbVWEqsCv6tbtkN19O"],"frameId":null,"index":"bI9","roundness":null,"seed":1450336391,"version":613,"versionNonce":1941121767,"isDeleted":false,"boundElements":[],"updated":1747092006709,"link":null,"locked":false,"points":[[0,0],[3.9034774574749775,0],[3.9034774574749775,18.47181296840838],[-0.13940990919545668,18.47181296840838],[0,0]],"lastCommittedPoint":null,"startBinding":null,"endBinding":null,"startArrowhead":null,"endArrowhead":null},{"id":"oR9aNwZoJlc2WFRb1WyMU","type":"line","x":47.544157395878756,"y":36.34094482820501,"width":4.042887366670434,"height":18.47181296840838,"angle":0,"strokeColor":"#000000","backgroundColor":"#ffffff","fillStyle":"solid","strokeWidth":1,"strokeStyle":"solid","roughness":1,"opacity":100,"groupIds":["pXwQsk9cJkaMNmeBLRnvQ","eY5BbVWEqsCv6tbtkN19O"],"frameId":null,"index":"bIA","roundness":null,"seed":1451407271,"version":692,"versionNonce":2046506503,"isDeleted":false,"boundElements":[],"updated":1747092006709,"link":null,"locked":false,"points":[[0,0],[3.9034774574749775,0],[3.9034774574749775,18.47181296840838],[-0.13940990919545668,18.47181296840838],[0,0]],"lastCommittedPoint":null,"startBinding":null,"endBinding":null,"startArrowhead":null,"endArrowhead":null},{"type":"text","version":2511,"versionNonce":223665447,"isDeleted":false,"id":"DTbi8MsraUns1S4PG0E4L","fillStyle":"solid","strokeWidth":1,"strokeStyle":"solid","roughness":0,"opacity":100,"angle":0,"x":0.0,"y":60.12140712463179,"strokeColor":"#000000","backgroundColor":"#fff","width":71.62530517578125,"height":37.67277411536633,"seed":482028231,"groupIds":["voEbQL2WWznJi1cwjxVHd","PhscBYg0MLlKs0D2scisD","3wztjwjMTSuE9M00P6olP","D-_3REbYIuzD0KOWcLVBS","9-meQ4p567C_DZXjcqQOO","7Si93L5aHgr48dS0yXopI","eY5BbVWEqsCv6tbtkN19O"],"strokeSharpness":"sharp","boundElements":[],"updated":1747092006709,"link":null,"fontSize":15.069109646146531,"fontFamily":1,"text":"Network\nInterface","baseline":34,"textAlign":"center","verticalAlign":"top","containerId":null,"originalText":"Network\nInterface","index":"bIB","frameId":null,"roundness":null,"locked":false,"autoResize":true,"lineHeight":1.25}],"appState":{"gridSize":null,"viewBackgroundColor":"transparent"},"files":{}}